<?xml version="1.0" encoding="utf-8"?>
<Container>
  <Beta>True</Beta>
<Category>Web:</Category>
  <Name>unifi</Name>
  <Description>
  Intuitive and Robust Configuration, Control and Monitoring. Instantly provision and configure thousands of UniFi APs. Quickly manage system traffic.
  </Description>
  <Registry>https://registry.hub.docker.com/u/cmtec/unifi-beta/</Registry>
  <Repository>cmtec/unifi-beta</Repository>
  <BindTime>true</BindTime>
  <Privileged>false</Privileged>
  <Networking>
    <Mode>bridge</Mode>
    <Publish>
      <Port>
        <HostPort>3478</HostPort>
        <ContainerPort>3478</ContainerPort>
        <Protocol>udp</Protocol>
      </Port>
      <Port>
        <HostPort>8080</HostPort>
        <ContainerPort>8080</ContainerPort>
        <Protocol>tcp</Protocol>
      </Port>
      <Port>
        <HostPort>8081</HostPort>
        <ContainerPort>8081</ContainerPort>
        <Protocol>tcp</Protocol>
      </Port>
      <Port>
        <HostPort>8443</HostPort>
        <ContainerPort>8443</ContainerPort>
        <Protocol>tcp</Protocol>
      </Port>
      <Port>
        <HostPort>8880</HostPort>
        <ContainerPort>8880</ContainerPort>
        <Protocol>tcp</Protocol>
      </Port>
    </Publish>
  </Networking>
  <Environment>
    <Variable>
      <Name></Name>
      <Value></Value>
    </Variable>
  </Environment>
  <Data>
     <Volume>
      <HostDir></HostDir>
      <ContainerDir>/config</ContainerDir>
      <Mode>rw</Mode>
    </Volume> 
  </Data>
  <WebUI>https://[IP]:[PORT:8443]/</WebUI>
  <Icon>https://dl.ubnt.com/press/Company_Logos/U_Logo/WEB/U_Logo_RGB.png</Icon>
  <Banner></Banner>
</Container>
